insupdel4stac/__init__.py
insupdel4stac/_version.py
insupdel4stac/connector.py
insupdel4stac/deleter.py
insupdel4stac/inserter.py
insupdel4stac/logger.py
insupdel4stac/main.py
insupdel4stac/py.typed
insupdel4stac/updater.py
insupdel4stac/analysers/__init__.py
insupdel4stac/analysers/existance_validator.py
insupdel4stac/analysers/properties_verifier.py
insupdel4stac/analysers/table_details.py
insupdel4stac/statics/__init__.py
insupdel4stac/statics/constants.py
insupdel4stac-2.0.7.dist-info/CC-BY-4.0.txt
insupdel4stac-2.0.7.dist-info/CC0-1.0.txt
insupdel4stac-2.0.7.dist-info/EUPL-1.2.txt
insupdel4stac-2.0.7.dist-info/METADATA
insupdel4stac-2.0.7.dist-info/WHEEL
insupdel4stac-2.0.7.dist-info/top_level.txt
insupdel4stac-2.0.7.dist-info/RECORD
